Metadata-Version: 1.1
Name: pycola
Version: 0.1.59
Summary: python package to parse the job bulletins and generate a structured file
Home-page: https://www.kaggle.com/shivamb/1-bulletin-structuring-engine-cola
Author: Shivam Bansal
Author-email: shivam5992@gmail.com
License: MIT
Keywords: text parsing,entity extraction,bulletin parser
Platform: UNKNOWN
Classifier: Development Status :: 3 - Alpha
Classifier: Topic :: Software Development :: Build Tools
Classifier: License :: OSI Approved :: MIT License
Classifier: Programming Language :: Python :: 3
